fastel/__init__.py
fastel/ads/__init__.py
fastel/ads/facebook/__init__.py
fastel/ads/facebook/conversion.py
fastel/auth/__init__.py
fastel/authorizers.py
fastel/cart/__init__.py
fastel/cart/base.py
fastel/cart/cart.py
fastel/cart/collections.py
fastel/cart/datastructures.py
fastel/cart/exceptions.py
fastel/cart/product_item.py
fastel/cart/product_items.py
fastel/cart/utils.py
fastel/collections.py
fastel/config.py
fastel/exceptions.py
fastel/jwt/__init__.py
fastel/jwt/decode_static.py
fastel/jwt/jwt_encoder.py
fastel/jwt/jwt_payload.py
fastel/jwt/kms_encode.py
fastel/jwt/pem_coder.py
fastel/logistics/__init__.py
fastel/logistics/common/__init__.py
fastel/logistics/common/helpers.py
fastel/logistics/common/models/__init__.py
fastel/logistics/ecpay/__init__.py
fastel/logistics/ecpay/gateway.py
fastel/logistics/ecpay/models/__init__.py
fastel/logistics/sf/__init__.py
fastel/logistics/sf/cryptor.py
fastel/logistics/sf/gateway.py
fastel/logistics/sf/ierror.py
fastel/logistics/sf/models/__init__.py
fastel/logistics/tcat/__init__.py
fastel/logistics/tcat/models.py
fastel/logistics/tcat/tcat.py
fastel/logistics/trackingmore/__init__.py
fastel/notif/__init__.py
fastel/notif/notifier.py
fastel/payment/__init__.py
fastel/payment/common/__init__.py
fastel/payment/common/helpers.py
fastel/payment/common/models/__init__.py
fastel/payment/common/models/callback.py
fastel/payment/common/models/invoice.py
fastel/payment/common/models/order.py
fastel/payment/cryptors.py
fastel/payment/ecpay/__init__.py
fastel/payment/ecpay/gateway.py
fastel/payment/ecpay/models/__init__.py
fastel/payment/ecpay/models/checkout.py
fastel/payment/ecpay/models/invoice.py
fastel/payment/ecpay/models/refund.py
fastel/payment/linepay/__init__.py
fastel/payment/linepay/exceptions.py
fastel/payment/linepay/gateway.py
fastel/payment/linepay/models/__init__.py
fastel/payment/linepay/models/checkout.py
fastel/payment/neweb/__init__.py
fastel/payment/neweb/gateway.py
fastel/payment/neweb/models/__init__.py
fastel-3.1.0.dist-info/LICENSE
fastel-3.1.0.dist-info/METADATA
fastel-3.1.0.dist-info/WHEEL
fastel-3.1.0.dist-info/RECORD
