Metadata-Version: 2.1
Name: fastel
Version: 3.1.0
Summary: RevtelTech Backend SDK
Author: Chien
Author-email: a0186163@gmail.com
Requires-Python: >=3.7,<4.0
Classifier: Programming Language :: Python :: 3
Classifier: Programming Language :: Python :: 3.7
Classifier: Programming Language :: Python :: 3.8
Classifier: Programming Language :: Python :: 3.9
Classifier: Programming Language :: Python :: 3.10
Classifier: Programming Language :: Python :: 3.11
Requires-Dist: PyJWT (>=2.2.0,<3.0.0)
Requires-Dist: beautifulsoup4 (>=4.11.1,<5.0.0)
Requires-Dist: boto3 (>=1.18.56,<2.0.0)
Requires-Dist: cryptography (>=35.0.0,<36.0.0)
Requires-Dist: facebook-business (>=12.0.1,<13.0.0)
Requires-Dist: fastapi (>=0.63.0)
Requires-Dist: google-auth (>=1.32.0,<2.0.0)
Requires-Dist: google-auth-oauthlib (>=0.4.4,<0.5.0)
Requires-Dist: pycrypto (>=2.6.1,<3.0.0)
Requires-Dist: pydantic[email] (>=1.8.2,<2.0.0)
Requires-Dist: pymongo (>=3.12.0,<4.0.0)
Requires-Dist: pytz (>=2022.1,<2023.0)
